vnpy_comstar/__init__.py
vnpy_comstar/gateway/__init__.py
vnpy_comstar/gateway/comstar_api.pyd
vnpy_comstar/gateway/comstar_gateway.py
vnpy_comstar/gateway/td_api.py
vnpy_comstar-1.0.3.dist-info/LICENSE
vnpy_comstar-1.0.3.dist-info/METADATA
vnpy_comstar-1.0.3.dist-info/WHEEL
vnpy_comstar-1.0.3.dist-info/top_level.txt
vnpy_comstar-1.0.3.dist-info/RECORD
